{
  "slug": "como-saber-se-sua-marca-parece-amadora",
  "title": "Como saber se sua marca parece amadora: sinais que afastam confiança",
  "description": "Veja os sinais mais comuns de que sua marca parece amadora e entenda como isso afeta percepção, confiança e fechamento de oportunidades.",
  "category": "Marca",
  "intro": "Muitas marcas não parecem amadoras por falta de talento, mas por falta de coerência visual e clareza de apresentação.",
  "tag": "Percepção",
  "readTime": "Leitura de 7 min",
  "tagColor": "#e76f51",
  "displayDate": "Publicado em 20 de abril de 2026",
  "datePublished": "2026-04-20",
  "order": 11
}
